monaco_qualifying/__init__.py
monaco_qualifying/__main__.py
monaco_qualifying/driver_3_version.py
monaco_qualifying/qualification_report.txt
monaco_qualifying/data/__init__.py
monaco_qualifying/data/abbreviations.txt
monaco_qualifying/data/end.log
monaco_qualifying/data/start.log
monaco_qualifying-0.1.29.dist-info/licenses/LICENSE
monaco_qualifying-0.1.29.dist-info/METADATA
monaco_qualifying-0.1.29.dist-info/WHEEL
monaco_qualifying-0.1.29.dist-info/entry_points.txt
monaco_qualifying-0.1.29.dist-info/top_level.txt
monaco_qualifying-0.1.29.dist-info/RECORD
