Metadata-Version: 2.4
Name: monaco_qualifying
Version: 0.1.29
Summary: Analysis of Formula 1 qualification results.
Author-email: Liliia Shpytsia <fioletowujsemizwetik@gmail.com>
License-Expression: MIT
Project-URL: Homepage, https://git.foxminded.ua/liliia-shpytsia-mentoring/task_6_report_of_monaco_2018_racing
Project-URL: Issues, https://git.foxminded.ua/liliia-shpytsia-mentoring/task_6_report_of_monaco_2018_racing/-/issues
Classifier: Programming Language :: Python :: 3
Classifier: Programming Language :: Python :: 3.10
Classifier: Operating System :: OS Independent
Requires-Python: >=3.10
License-File: LICENSE
Provides-Extra: dev
Requires-Dist: pytest>=7.0.0; extra == "dev"
Dynamic: license-file
